zc.zodbdgc-1.1.0-py3.9-nspkg.pth
zc/zodbdgc/README.test
zc/zodbdgc/README.txt
zc/zodbdgc/__init__.py
zc/zodbdgc/oidset.test
zc/zodbdgc/tests.py
zc.zodbdgc-1.1.0.dist-info/METADATA
zc.zodbdgc-1.1.0.dist-info/WHEEL
zc.zodbdgc-1.1.0.dist-info/entry_points.txt
zc.zodbdgc-1.1.0.dist-info/namespace_packages.txt
zc.zodbdgc-1.1.0.dist-info/top_level.txt
zc.zodbdgc-1.1.0.dist-info/RECORD
