Metadata-Version: 2.1
Name: zc.zodbdgc
Version: 1.1.0
Summary: ZODB Distributed Garbage Collection
Home-page: https://github.com/zopefoundation/zc.zodbdgc
Author: Jim Fulton
Author-email: jim@zope.com
License: ZPL 2.1
Keywords: database nosql python zope zodb garbage collection distributed
Platform: UNKNOWN
Classifier: Framework :: ZODB
Classifier: License :: OSI Approved :: Zope Public License
Classifier: Operating System :: OS Independent
Classifier: Programming Language :: Python
Classifier: Programming Language :: Python :: 2
Classifier: Programming Language :: Python :: 2.7
Classifier: Programming Language :: Python :: 3
Classifier: Programming Language :: Python :: 3.5
Classifier: Programming Language :: Python :: 3.6
Classifier: Programming Language :: Python :: 3.7
Classifier: Programming Language :: Python :: 3.8
Classifier: Programming Language :: Python :: 3.9
Classifier: Programming Language :: Python :: Implementation :: CPython
Classifier: Programming Language :: Python :: Implementation :: PyPy
Requires-Dist: BTrees (>=4.0.0)
Requires-Dist: ZODB (>=5.1.0)
Requires-Dist: persistent (>=4.0.0)
Requires-Dist: setuptools (>=17.1)
Requires-Dist: transaction
Requires-Dist: zodbpickle
Provides-Extra: test
Requires-Dist: zope.testing ; extra == 'test'
Requires-Dist: mock (>=1.3.0) ; extra == 'test'
Requires-Dist: zope.testrunner ; extra == 'test'
